netapp_ocum/__init__.py
netapp_ocum/client.py
netapp_ocum/client_test.py
netapp_ocum/http.py
netapp_ocum/http_test.py
netapp_ocum/settings.py
netapp_ocum/settings_test.py
netapp_ocum/objects/__init__.py
netapp_ocum/objects/aggregate.py
netapp_ocum/objects/aggregate_test.py
netapp_ocum/objects/base.py
netapp_ocum/objects/base_test.py
netapp_ocum/objects/cluster.py
netapp_ocum/objects/cluster_test.py
netapp_ocum/objects/interface.py
netapp_ocum/objects/interface_test.py
netapp_ocum/objects/lun.py
netapp_ocum/objects/lun_test.py
netapp_ocum/objects/namespace.py
netapp_ocum/objects/namespace_test.py
netapp_ocum/objects/node.py
netapp_ocum/objects/node_test.py
netapp_ocum/objects/port.py
netapp_ocum/objects/port_test.py
netapp_ocum/objects/svm.py
netapp_ocum/objects/svm_test.py
netapp_ocum/objects/volume.py
netapp_ocum/objects/volume_test.py
netapp_ocum-0.1.8.dist-info/LICENSE
netapp_ocum-0.1.8.dist-info/METADATA
netapp_ocum-0.1.8.dist-info/WHEEL
netapp_ocum-0.1.8.dist-info/top_level.txt
netapp_ocum-0.1.8.dist-info/RECORD
