Metadata-Version: 2.1
Name: netapp_ocum
Version: 0.1.8
Summary: Client bindings for for the NetApp OnCommand Unified Manager (OCUM) REST API.
Home-page: http://github.com/powerhome/python-netapp-ocum
Author: PowerHRG
Author-email: phrgadmin@powerhrg.com
License: GPLv3
Keywords: netapp nfs api http ocum
Classifier: Development Status :: 3 - Alpha
Classifier: Environment :: Console
Classifier: License :: OSI Approved :: GNU General Public License v3 or later (GPLv3+)
Classifier: Natural Language :: English
Classifier: Operating System :: POSIX
Classifier: Programming Language :: Python
Classifier: Topic :: Software Development :: User Interfaces
Classifier: Topic :: Terminals
License-File: LICENSE
